pyCeph/__init__.py
pyCeph/aios3.py
pyCeph/crypto.py
pyCeph/log.py
pyCeph/s3.py
pyCeph-0.5.3.dist-info/LICENSE
pyCeph-0.5.3.dist-info/METADATA
pyCeph-0.5.3.dist-info/WHEEL
pyCeph-0.5.3.dist-info/top_level.txt
pyCeph-0.5.3.dist-info/RECORD
